nauyaca/__init__.py
nauyaca/__main__.py
nauyaca/client/__init__.py
nauyaca/client/protocol.py
nauyaca/client/session.py
nauyaca/content/__init__.py
nauyaca/content/gemtext.py
nauyaca/content/templates.py
nauyaca/protocol/__init__.py
nauyaca/protocol/constants.py
nauyaca/protocol/request.py
nauyaca/protocol/response.py
nauyaca/protocol/status.py
nauyaca/py.typed
nauyaca/security/__init__.py
nauyaca/security/certificates.py
nauyaca/security/pyopenssl_tls.py
nauyaca/security/tls.py
nauyaca/security/tofu.py
nauyaca/server/__init__.py
nauyaca/server/config.py
nauyaca/server/handler.py
nauyaca/server/location.py
nauyaca/server/middleware.py
nauyaca/server/protocol.py
nauyaca/server/proxy.py
nauyaca/server/reload/__init__.py
nauyaca/server/reload/config.py
nauyaca/server/reload/supervisor.py
nauyaca/server/reload/watcher.py
nauyaca/server/router.py
nauyaca/server/server.py
nauyaca/server/tls_protocol.py
nauyaca/utils/__init__.py
nauyaca/utils/logging.py
nauyaca/utils/url.py
nauyaca-0.10.0.dist-info/WHEEL
nauyaca-0.10.0.dist-info/entry_points.txt
nauyaca-0.10.0.dist-info/METADATA
nauyaca-0.10.0.dist-info/RECORD
