Metadata-Version: 2.3
Name: nauyaca
Version: 0.10.0
Summary: Modern Gemini protocol server and client implementation using asyncio
Keywords: gemini,protocol,server,client,asyncio,networking
Author: Alan Velasco
Author-email: Alan Velasco <alan@alanbato.com>
License: MIT
Classifier: Development Status :: 3 - Alpha
Classifier: Intended Audience :: Developers
Classifier: License :: OSI Approved :: MIT License
Classifier: Programming Language :: Python :: 3
Classifier: Programming Language :: Python :: 3.10
Classifier: Programming Language :: Python :: 3.11
Classifier: Programming Language :: Python :: 3.12
Classifier: Programming Language :: Python :: 3.13
Classifier: Programming Language :: Python :: 3.14
Classifier: Topic :: Internet :: WWW/HTTP :: HTTP Servers
Classifier: Topic :: Software Development :: Libraries :: Python Modules
Classifier: Framework :: AsyncIO
Requires-Dist: cryptography>=46.0.3
Requires-Dist: pyopenssl>=24.0.0
Requires-Dist: rich>=14.2.0
Requires-Dist: structlog>=25.5.0
Requires-Dist: tomli>=2.0.0 ; python_full_version < '3.11'
Requires-Dist: tomli-w>=1.0.0
Requires-Dist: typer>=0.20.0
Requires-Dist: watchfiles>=0.20.0 ; extra == 'reload'
Requires-Python: >=3.10
Project-URL: Repository, https://github.com/alanbato/nauyaca
Project-URL: Bug Tracker, https://github.com/alanbato/nauyaca/issues
Provides-Extra: reload
